{
    "video_id": "ed60dcdb-b273-44e7-b5dc-f9527d7c403f",
    "source_video_uid": "d7a2e92e-dc74-4e79-be04-a86f829fc3ec",
    "target_video_uid": "ed60dcdb-b273-44e7-b5dc-f9527d7c403f",
    "source_file_name": "d7a2e92e-dc74-4e79-be04-a86f829fc3ec_updated.json",
    "target_file_name": "ed60dcdb-b273-44e7-b5dc-f9527d7c403f_updated.json",
    "target_equal_ratio": 0.6666666666666666,
    "trial_index": 9,
    "spatial_data": [
        {
            "object_id": 1,
            "object_name": "sausage",
            "init_status": {
                "status": "raw",
                "container": null
            }
        },
        {
            "object_id": 2,
            "object_name": "chicken",
            "init_status": {
                "status": "cooked",
                "container": 3
            }
        },
        {
            "object_id": 3,
            "object_name": "grill",
            "init_status": {
                "status": "off",
                "container": null
            }
        },
        {
            "object_id": 4,
            "object_name": "charcoal bag",
            "init_status": {
                "status": "full",
                "container": null
            }
        },
        {
            "object_id": 5,
            "object_name": "charcoal",
            "init_status": {
                "status": "unlit",
                "container": 4
            }
        },
        {
            "object_id": 6,
            "object_name": "player",
            "init_status": {
                "status": "stand",
                "container": null
            }
        },
        {
            "object_id": 7,
            "object_name": "plate",
            "init_status": {
                "status": "default",
                "container": null
            }
        },
        {
            "object_id": 8,
            "object_name": "sausage",
            "init_status": {
                "status": "raw",
                "container": null
            }
        },
        {
            "object_id": 9,
            "object_name": "piping bag",
            "init_status": {
                "status": "default",
                "container": null
            }
        },
        {
            "object_id": 10,
            "object_name": "mat",
            "init_status": {
                "status": "default",
                "container": null
            }
        },
        {
            "object_id": 11,
            "object_name": "salad",
            "init_status": {
                "status": "default",
                "container": null
            }
        },
        {
            "object_id": 12,
            "object_name": "corn dogs",
            "init_status": {
                "status": "default",
                "container": null
            }
        },
        {
            "object_id": 13,
            "object_name": "seaweed",
            "init_status": {
                "status": "default",
                "container": null
            }
        },
        {
            "object_id": 14,
            "object_name": "oil",
            "init_status": {
                "status": "default",
                "container": null
            }
        },
        {
            "object_id": 15,
            "object_name": "burritos",
            "init_status": {
                "status": "default",
                "container": null
            }
        },
        {
            "object_id": 16,
            "object_name": "lime juice",
            "init_status": {
                "status": "default",
                "container": null
            }
        },
        {
            "object_id": 17,
            "object_name": "green pepper",
            "init_status": {
                "status": "default",
                "container": null
            }
        },
        {
            "object_id": 18,
            "object_name": "goyna bori",
            "init_status": {
                "status": "default",
                "container": null
            }
        },
        {
            "object_id": 19,
            "object_name": "pancake",
            "init_status": {
                "status": "default",
                "container": null
            }
        },
        {
            "object_id": 20,
            "object_name": "breadsticks",
            "init_status": {
                "status": "default",
                "container": null
            }
        },
        {
            "object_id": 21,
            "object_name": "onion",
            "init_status": {
                "status": "default",
                "container": null
            }
        },
        {
            "object_id": 22,
            "object_name": "hotdog",
            "init_status": {
                "status": "default",
                "container": null
            }
        },
        {
            "object_id": 23,
            "object_name": "walnut",
            "init_status": {
                "status": "default",
                "container": null
            }
        },
        {
            "object_id": 24,
            "object_name": "cashew nut",
            "init_status": {
                "status": "default",
                "container": null
            }
        },
        {
            "object_id": 25,
            "object_name": "liver",
            "init_status": {
                "status": "default",
                "container": null
            }
        },
        {
            "object_id": 26,
            "object_name": "corn",
            "init_status": {
                "status": "default",
                "container": null
            }
        },
        {
            "object_id": 27,
            "object_name": "mango",
            "init_status": {
                "status": "default",
                "container": null
            }
        },
        {
            "object_id": 28,
            "object_name": "tahini",
            "init_status": {
                "status": "default",
                "container": null
            }
        },
        {
            "object_id": 29,
            "object_name": "green bean",
            "init_status": {
                "status": "default",
                "container": null
            }
        },
        {
            "object_id": 30,
            "object_name": "salt",
            "init_status": {
                "status": "default",
                "container": null
            }
        },
        {
            "object_id": 31,
            "object_name": "radish",
            "init_status": {
                "status": "default",
                "container": null
            }
        },
        {
            "object_id": 32,
            "object_name": "cake",
            "init_status": {
                "status": "default",
                "container": null
            }
        },
        {
            "object_id": 33,
            "object_name": "pastry",
            "init_status": {
                "status": "default",
                "container": null
            }
        },
        {
            "object_id": 34,
            "object_name": "amaro",
            "init_status": {
                "status": "default",
                "container": null
            }
        },
        {
            "object_id": 35,
            "object_name": "cottage cheese",
            "init_status": {
                "status": "default",
                "container": null
            }
        },
        {
            "object_id": 36,
            "object_name": "brussel sprouts",
            "init_status": {
                "status": "default",
                "container": null
            }
        },
        {
            "object_id": 37,
            "object_name": "yam",
            "init_status": {
                "status": "default",
                "container": null
            }
        },
        {
            "object_id": 38,
            "object_name": "grapes",
            "init_status": {
                "status": "default",
                "container": null
            }
        },
        {
            "object_id": 39,
            "object_name": "croissant",
            "init_status": {
                "status": "default",
                "container": null
            }
        },
        {
            "object_id": 40,
            "object_name": "bacon",
            "init_status": {
                "status": "default",
                "container": null
            }
        },
        {
            "object_id": 41,
            "object_name": "spice grinder",
            "init_status": {
                "status": "default",
                "container": null
            }
        },
        {
            "object_id": 42,
            "object_name": "weight scale",
            "init_status": {
                "status": "default",
                "container": null
            }
        },
        {
            "object_id": 43,
            "object_name": "wok",
            "init_status": {
                "status": "default",
                "container": null
            }
        },
        {
            "object_id": 44,
            "object_name": "plastic bag",
            "init_status": {
                "status": "default",
                "container": null
            }
        },
        {
            "object_id": 45,
            "object_name": "ziplock bag",
            "init_status": {
                "status": "default",
                "container": null
            }
        },
        {
            "object_id": 46,
            "object_name": "packet",
            "init_status": {
                "status": "default",
                "container": null
            }
        },
        {
            "object_id": 47,
            "object_name": "knife",
            "init_status": {
                "status": "default",
                "container": null
            }
        },
        {
            "object_id": 48,
            "object_name": "grater",
            "init_status": {
                "status": "default",
                "container": null
            }
        },
        {
            "object_id": 49,
            "object_name": "pot",
            "init_status": {
                "status": "default",
                "container": null
            }
        },
        {
            "object_id": 50,
            "object_name": "deep fryer",
            "init_status": {
                "status": "default",
                "container": null
            }
        },
        {
            "object_id": 51,
            "object_name": "wash basin",
            "init_status": {
                "status": "default",
                "container": null
            }
        },
        {
            "object_id": 52,
            "object_name": "stove",
            "init_status": {
                "status": "default",
                "container": null
            }
        }
    ]
}